aiomultitask/__init__.py
aiomultitask/__version__.py
aiomultitask-0.0.1.dev1.dist-info/LICENSE
aiomultitask-0.0.1.dev1.dist-info/METADATA
aiomultitask-0.0.1.dev1.dist-info/WHEEL
aiomultitask-0.0.1.dev1.dist-info/top_level.txt
aiomultitask-0.0.1.dev1.dist-info/RECORD
